MANIFEST.in
README.rst
s3dependencies.py
setup.py
s3sourcedependencies.egg-info/PKG-INFO
s3sourcedependencies.egg-info/SOURCES.txt
s3sourcedependencies.egg-info/dependency_links.txt
s3sourcedependencies.egg-info/entry_points.txt
s3sourcedependencies.egg-info/requires.txt
s3sourcedependencies.egg-info/top_level.txt