Metadata-Version: 1.0
Name: s3sourcedependencies
Version: 0.1
Summary: Download and install from private source distributions hosted on Amazon S3.
Home-page: https://bitbucket.org/delinhabit/s3sourcedependencies
Author: Ion Scerbatiuc
Author-email: delinhabit@gmail.com
License: BSD
Keywords: setuptools s3 dependencies s3sourceuploader
Platform: UNKNOWN
Classifier: Development Status :: 4 - Beta
Classifier: Intended Audience :: Developers
Classifier: License :: OSI Approved :: Python Software Foundation License
Classifier: Operating System :: OS Independent
Classifier: Programming Language :: Python
